django_sysinfo/__init__.py
django_sysinfo/api.py
django_sysinfo/compat.py
django_sysinfo/conf.py
django_sysinfo/urls.py
django_sysinfo/utils.py
django_sysinfo/version.py
django_sysinfo/views.py
django_sysinfo/static/sysinfo/sysinfo.css
django_sysinfo/static/sysinfo/sysinfo.css.map
django_sysinfo/static/sysinfo/sysinfo.scss
django_sysinfo/templates/admin/sysinfo/checks_section.html
django_sysinfo/templates/admin/sysinfo/environ_section.html
django_sysinfo/templates/admin/sysinfo/extra_section.html
django_sysinfo/templates/admin/sysinfo/host_section.html
django_sysinfo/templates/admin/sysinfo/modules_section.html
django_sysinfo/templates/admin/sysinfo/os_section.html
django_sysinfo/templates/admin/sysinfo/process_section.html
django_sysinfo/templates/admin/sysinfo/project_section.html
django_sysinfo/templates/admin/sysinfo/python_section.html
django_sysinfo/templates/admin/sysinfo/sysinfo.html
django_sysinfo/templates/admin/sysinfo/sysinfo_section.html
django_sysinfo/templatetags/__init__.py
django_sysinfo/templatetags/sysinfo.py
django_sysinfo-2.7.0.dist-info/METADATA
django_sysinfo-2.7.0.dist-info/WHEEL
django_sysinfo-2.7.0.dist-info/licenses/LICENSE
django_sysinfo-2.7.0.dist-info/RECORD
